pyutil_mk1/__init__.py
pyutil_mk1/arg_util.py
pyutil_mk1/dict_string_util.py
pyutil_mk1/extract_urls.py
pyutil_mk1/find_children_dirs_containing_files.py
pyutil_mk1/find_dirs_containing_content.py
pyutil_mk1/fs_util.py
pyutil_mk1/jsonrw.py
pyutil_mk1/parse_file_lines.py
pyutil_mk1/path_util.py
pyutil_mk1/platform_bind_util.py
pyutil_mk1/random_files.py
pyutil_mk1/time_conversion_util.py
pyutil_mk1/web_tool.py
pyutil_mk1-0.0.1.dist-info/LICENSE.txt
pyutil_mk1-0.0.1.dist-info/METADATA
pyutil_mk1-0.0.1.dist-info/WHEEL
pyutil_mk1-0.0.1.dist-info/top_level.txt
pyutil_mk1-0.0.1.dist-info/RECORD
